django_router-1.0.8.dist-info/METADATA
django_router-1.0.8.dist-info/WHEEL
django_router-1.0.8.dist-info/licenses/LICENSE
django_router/__init__.py
django_router/apps.py
django_router/management/__init__.py
django_router/management/commands/__init__.py
django_router/management/commands/router_list.py
django_router/management/commands/router_urls.py
django_router/settings.py
django_router/utils.py
django_router-1.0.8.dist-info/RECORD
