Metadata-Version: 2.1
Name: django-router
Version: 1.0.8
Summary: Use simple decorators on views instead of maintaining lengthy urls.py
Author-Email: RealGecko <alexandrbezenkov@gmail.com>
License: BSD-3-Clause
Requires-Python: >=3.7
